.coveragerc
.gitignore
Dockerfile
Makefile
README.rst
docker-compose.yml
pytest.ini
requirements.txt
setup.py
radical/__init__.py
radical/client.py
radical/decorators.py
radical/demo.py
radical/exceptions.py
radical/log.py
radical/meta.py
radical/peer.py
radical/tests.py
radical/worker.py
radical/contrib/__init__.py
radical/contrib/django/__init__.py
radical/contrib/django/client.py
radical/management/__init__.py
radical/management/commands/__init__.py
radical/management/commands/radical.py
radical/serialization/__init__.py
radical/serialization/base.py
radical/serialization/json.py
radical/serialization/pickle.py
radical/transports/postgres.py
radical/transports/redis.py
radical_rpc.egg-info/PKG-INFO
radical_rpc.egg-info/SOURCES.txt
radical_rpc.egg-info/dependency_links.txt
radical_rpc.egg-info/entry_points.txt
radical_rpc.egg-info/not-zip-safe
radical_rpc.egg-info/requires.txt
radical_rpc.egg-info/top_level.txt